nb2kg/__init__.py
nb2kg/_version.py
nb2kg/handlers.py
nb2kg/managers.py
nb2kg-0.7.0.dist-info/LICENSE.md
nb2kg-0.7.0.dist-info/METADATA
nb2kg-0.7.0.dist-info/WHEEL
nb2kg-0.7.0.dist-info/top_level.txt
nb2kg-0.7.0.dist-info/RECORD
