Metadata-Version: 2.1
Name: nb2kg
Version: 0.7.0
Summary: Extension for Jupyter Notebook 4.2.x to enable remote kernels hosted by Kernel Gateway or Enterprise Gateway
Home-page: https://github.com/jupyter-incubator/nb2kg
Author: Jupyter Development Team
Author-email: jupyter@googlegroups.com
License: BSD
Platform: Jupyter Notebook 4.2.x
Classifier: Intended Audience :: Developers
Classifier: Intended Audience :: System Administrators
Classifier: Intended Audience :: Science/Research
Classifier: License :: OSI Approved :: BSD License
Classifier: Programming Language :: Python
Classifier: Programming Language :: Python :: 2
Classifier: Programming Language :: Python :: 3
Requires-Dist: notebook (<6.0,>=4.2.0)
